lbpackages/__init__.py
lbpackages/classes/__init__.py
lbpackages/classes/dbclient.py
lbpackages/classes/stocks.py
lbpackages/createdb/__init__.py
lbpackages/createdb/create_tables.py
lbclasses-0.1.2.dist-info/WHEEL
lbclasses-0.1.2.dist-info/METADATA
lbclasses-0.1.2.dist-info/RECORD
