Metadata-Version: 2.1
Name: lbclasses
Version: 0.1.2
Summary: Implements classes for stocks model and db client
Author: Lionel Barbagallo
Requires-Python: >=3.7.10,<4.0.0
Classifier: Programming Language :: Python :: 3
Classifier: Programming Language :: Python :: 3.10
Classifier: Programming Language :: Python :: 3.8
Classifier: Programming Language :: Python :: 3.9
Requires-Dist: SQLAlchemy (>=1.4.26,<2.0.0)
